LICENSE
LICENSE-APPENDIX.md
SECURITY.md
STUB-README.md
pe_packer_stub.py
rust_python_pe_packer-0.0.5.dist-info/METADATA
rust_python_pe_packer-0.0.5.dist-info/WHEEL
rust_python_pe_packer-0.0.5.dist-info/entry_points.txt
rust_python_pe_packer-0.0.5.dist-info/licenses/LICENSE
rust_python_pe_packer-0.0.5.dist-info/licenses/LICENSE-APPENDIX.md
rust_python_pe_packer-0.0.5.dist-info/RECORD
