Metadata-Version: 2.4
Name: rust-python-pe-packer
Version: 0.0.5
Summary: Educational Rust/Python PE (Portable Executable) learning stub. No packing functionality. See SECURITY.md.
Project-URL: Homepage, https://github.com/codeamt/rust-python-pe-packer
Project-URL: Documentation, https://github.com/codeamt/rust-python-pe-packer#readme
Project-URL: Security, https://github.com/codeamt/rust-python-pe-packer/blob/main/SECURITY.md
Project-URL: License, https://github.com/codeamt/rust-python-pe-packer/blob/main/LICENSE-APPENDIX.md
Author-email: AnnMargaret Tutu <annmargaret.mailforce@gmail.com>
License: Apache-2.0; see LICENSE-APPENDIX.md for educational-use clarifications
License-File: LICENSE
License-File: LICENSE-APPENDIX.md
Keywords: defensive security,malware analysis training,portable executable,reverse engineering education,software forensics education,unpacking research (educational)
Classifier: Development Status :: 3 - Alpha
Classifier: Intended Audience :: Education
Classifier: License :: OSI Approved :: Apache Software License
Classifier: Programming Language :: Python :: 3
Classifier: Programming Language :: Python :: 3 :: Only
Classifier: Topic :: Education
Classifier: Topic :: Security
Requires-Python: >=3.8
